LICENSE
MANIFEST.in
README.md
setup.py
cf/__init__.py
cf/__main__.py
cf/blog.py
cf/bloguser.py
cf/classes.py
cf/compare.py
cf/contest_list.py
cf/conteststatus.py
cf/problems.py
cf/ratingchange.py
cf/user_info.py
cf/user_rating.py
cf/userstatus.py
cf/util.py
cfs.egg-info/PKG-INFO
cfs.egg-info/SOURCES.txt
cfs.egg-info/dependency_links.txt
cfs.egg-info/entry_points.txt
cfs.egg-info/requires.txt
cfs.egg-info/top_level.txt
images/blog.png
images/compare.png
images/contest.png
images/logo.png
images/rating_change.png
images/show_user.png
images/submissions_contest.png
images/submissions_user.png
images/user_graph.png