Metadata-Version: 2.1
Name: cfs
Version: 1.0.4
Summary: Codeforces cli for lazy nerds who don't want to leave their cozy terminals.
Home-page: https://github.com/prasoonbatham11/cfcli
Author: Prasoon Batham
Author-email: prasoonbatham@gmail.com
License: MIT
Keywords: Codeforces,cli,command line,terminal
Platform: UNKNOWN
Requires: requests
Requires: prettytable
Requires: bs4
Requires: colorama
Requires: numpy
Requires: mdv
Requires: html2text
Requires: gnuplotlib
Requires: termgraph
Requires: yaspin
Requires-Python: >=3.6
